packaging/__init__.py
packaging/perceptron.py
perceptron_pkg_deftydev-0.0.5.dist-info/LICENSE
perceptron_pkg_deftydev-0.0.5.dist-info/METADATA
perceptron_pkg_deftydev-0.0.5.dist-info/WHEEL
perceptron_pkg_deftydev-0.0.5.dist-info/top_level.txt
perceptron_pkg_deftydev-0.0.5.dist-info/RECORD
